{
  "content": [
    {
      "content": null,
      "created": "2022-07-18T02:20:59.445423Z",
      "format": null,
      "last_modified": "2022-07-17T10:44:13.116131Z",
      "mimetype": null,
      "name": "gauss_machine.ipynb",
      "path": "jupyterlite-demo/pyolite/pyb2d/gauss_machine.ipynb",
      "size": 4118,
      "type": "notebook",
      "writable": true
    },
    {
      "content": null,
      "created": "2022-07-18T02:20:59.442369Z",
      "format": null,
      "last_modified": "2022-07-17T10:44:13.115569Z",
      "mimetype": null,
      "name": "0_tutorial.ipynb",
      "path": "jupyterlite-demo/pyolite/pyb2d/0_tutorial.ipynb",
      "size": 18685,
      "type": "notebook",
      "writable": true
    },
    {
      "content": null,
      "created": "2022-07-18T02:20:59.442945Z",
      "format": null,
      "last_modified": "2022-07-17T10:44:13.115692Z",
      "mimetype": null,
      "name": "color_mixing.ipynb",
      "path": "jupyterlite-demo/pyolite/pyb2d/color_mixing.ipynb",
      "size": 3737,
      "type": "notebook",
      "writable": true
    },
    {
      "content": null,
      "created": "2022-07-18T02:20:59.445831Z",
      "format": null,
      "last_modified": "2022-07-17T10:44:13.116196Z",
      "mimetype": null,
      "name": "newtons_cradle.ipynb",
      "path": "jupyterlite-demo/pyolite/pyb2d/newtons_cradle.ipynb",
      "size": 3704,
      "type": "notebook",
      "writable": true
    },
    {
      "content": null,
      "created": "2022-07-18T02:20:59.444791Z",
      "format": null,
      "last_modified": "2022-07-18T02:20:59.444791Z",
      "mimetype": null,
      "name": "games",
      "path": "jupyterlite-demo/pyolite/pyb2d/games",
      "size": null,
      "type": "directory",
      "writable": true
    }
  ],
  "created": "2022-07-18T02:20:59.445601Z",
  "format": "json",
  "last_modified": "2022-07-18T02:20:59.445601Z",
  "mimetype": null,
  "name": "pyb2d",
  "path": "jupyterlite-demo/pyolite/pyb2d",
  "size": null,
  "type": "directory",
  "writable": true
}