{
  "content": [
    {
      "content": null,
      "created": "2022-07-20T16:56:41.280004Z",
      "format": null,
      "last_modified": "2022-07-20T16:54:37.828800Z",
      "mimetype": null,
      "name": "pythagorean.ipynb",
      "path": "divemath/pythagorean.ipynb",
      "size": 71031,
      "type": "notebook",
      "writable": true
    }
  ],
  "created": "2022-07-20T16:56:41.280004Z",
  "format": "json",
  "last_modified": "2022-07-20T16:56:41.280004Z",
  "mimetype": null,
  "name": "divemath",
  "path": "divemath",
  "size": null,
  "type": "directory",
  "writable": true
}